trie_memoize/__init__.py
trie_memoize-0.1.1.dist-info/entry_points.txt
trie_memoize-0.1.1.dist-info/LICENSE
trie_memoize-0.1.1.dist-info/WHEEL
trie_memoize-0.1.1.dist-info/METADATA
trie_memoize-0.1.1.dist-info/RECORD
